obraz/__init__.py
obraz/scaffold/_config.yml
obraz/scaffold/_layouts/default.html
obraz/scaffold/_layouts/post.html
obraz/scaffold/_posts/2014-01-01-welcome-to-obraz.md
obraz/scaffold/css/main.css
obraz/scaffold/index.html
obraz-0.9.5.dist-info/entry_points.txt
obraz-0.9.5.dist-info/LICENSE
obraz-0.9.5.dist-info/WHEEL
obraz-0.9.5.dist-info/METADATA
obraz-0.9.5.dist-info/RECORD
